mygene/__init__.py
mygene-3.2.2.dist-info/LICENSE.txt
mygene-3.2.2.dist-info/METADATA
mygene-3.2.2.dist-info/WHEEL
mygene-3.2.2.dist-info/top_level.txt
mygene-3.2.2.dist-info/RECORD
